{
  "dialogueTimeSec": 25,
  "coloredTexts": [
    {
      "hexColor": "#000000",
      "text": "In the Oceans you can find Shipwrecks that can contain maps to true Buried Treasures."
    },
    {
      "hexColor": "#000000",
      "text": "A desert and a snowy forest together!? Who make this map?"
    },
    {
      "hexColor": "#000000",
      "text": "Hope the Fisherman sails soon, I need some ink sacks."
    },
    {
      "hexColor": "#000000",
      "text": "Hello adventurer, hope you get your map ready for exploration."
    },
    {
      "hexColor": "#000000",
      "text": "Circular? What a ridiculous theory about our planet."
    },
    {
      "hexColor": "#000000",
      "text": "Don't touch anything please, you could ruin the ink."
    }
  ]
}