{
  "dialogueTimeSec": 25,
  "coloredTexts": [
    {
      "hexColor": "#000000",
      "text": "The Backpack has hard quests, but their skins are totally worth it"
    },
    {
      "hexColor": "#000000",
      "text": "I work alongside the butcher, but sometimes I think he's a bit weird."
    },
    {
      "hexColor": "#000000",
      "text": "This here, this there, and that's it! Some nice boots."
    },
    {
      "hexColor": "#000000",
      "text": "Leather is used for almost everything, you can even eat it!"
    },
    {
      "hexColor": "#000000",
      "text": "There are other animals you can get leather from besides cows."
    },
    {
      "hexColor": "#000000",
      "text": "A great leather craft is not just a piece of leather. It’s a piece of art."
    }
  ]
}